LICENSE
MANIFEST.in
README.md
setup.py
stochasticdp/__init__.py
stochasticdp/stochasticdp.py
stochasticdp.egg-info/PKG-INFO
stochasticdp.egg-info/SOURCES.txt
stochasticdp.egg-info/dependency_links.txt
stochasticdp.egg-info/top_level.txt