Metadata-Version: 1.0
Name: stochasticdp
Version: 0.4
Summary: 
Home-page: https://github.com/nelsonuhan/stochasticdp
Author: Nelson Uhan
Author-email: nelson@uhan.me
License: MIT
Platform: UNKNOWN
